PotSql/__init__.py
PotSql/mysql.py
PotSql-1.0.dist-info/METADATA
PotSql-1.0.dist-info/WHEEL
PotSql-1.0.dist-info/top_level.txt
PotSql-1.0.dist-info/RECORD
