Metadata-Version: 2.1
Name: PotSql
Version: 1.0
Summary: MySQL Library
Home-page: https://github.com/ForestBu/PotSql
Author: ForestBu
Author-email: tvc55.admn@gmail.com
Keywords: mysql MySQL MySql requests request query
Classifier: Programming Language :: Python :: 3.11
Classifier: License :: OSI Approved :: MIT License
Classifier: Operating System :: OS Independent
Requires-Python: >=3.11
Requires-Dist: requests >=2.25.1
